LICENSE
MANIFEST.in
README.rst
requirements.txt
setup.py
version.py
alignak_checks_wmi/__init__.py
alignak_checks_wmi/__init__.pyc
alignak_checks_wmi.egg-info/PKG-INFO
alignak_checks_wmi.egg-info/SOURCES.txt
alignak_checks_wmi.egg-info/dependency_links.txt
alignak_checks_wmi.egg-info/not-zip-safe
alignak_checks_wmi.egg-info/top_level.txt
alignak_checks_wmi/etc/arbiter/packs/resource.d/wmi.cfg
alignak_checks_wmi/etc/arbiter/packs/wmi/commands.cfg
alignak_checks_wmi/etc/arbiter/packs/wmi/groups.cfg
alignak_checks_wmi/etc/arbiter/packs/wmi/services.cfg
alignak_checks_wmi/etc/arbiter/packs/wmi/templates.cfg
alignak_checks_wmi/libexec/check_wmi_plus.README.txt
alignak_checks_wmi/libexec/check_wmi_plus.conf
alignak_checks_wmi/libexec/check_wmi_plus.makeman.sh
alignak_checks_wmi/libexec/check_wmi_plus.pl
alignak_checks_wmi/libexec/event_generic.pl
alignak_checks_wmi/libexec/utils.pm
alignak_checks_wmi/libexec/wmic
alignak_checks_wmi/libexec/check_wmi_plus.d/CommandExamples.chtml
alignak_checks_wmi/libexec/check_wmi_plus.d/README.txt
alignak_checks_wmi/libexec/check_wmi_plus.d/WarnCritExamples.chtml
alignak_checks_wmi/libexec/check_wmi_plus.d/check_sql.ini
alignak_checks_wmi/libexec/check_wmi_plus.d/check_wmi_plus.ini
alignak_checks_wmi/libexec/check_wmi_plus.d/checkexchange.ini
alignak_checks_wmi/libexec/check_wmi_plus.d/checkiis.ini
alignak_checks_wmi/libexec/check_wmi_plus.d/events.ini
alignak_checks_wmi/libexec/check_wmi_plus.d/samples.ini
alignak_checks_wmi/libexec/check_wmi_plus.d/test.ini
alignak_checks_wmi/libexec/check_wmi_plus.data/check_wmi_plus.compiledini